whereami_cli/__init__.py
whereami_cli/location.py
whereami_cli-0.1.1.dist-info/licenses/LICENSE
whereami_cli-0.1.1.dist-info/METADATA
whereami_cli-0.1.1.dist-info/WHEEL
whereami_cli-0.1.1.dist-info/entry_points.txt
whereami_cli-0.1.1.dist-info/top_level.txt
whereami_cli-0.1.1.dist-info/RECORD
