Metadata-Version: 2.4
Name: whereami-cli
Version: 0.1.1
Summary: 用于获取当前用户的经纬度位置信息的命令行工具
Home-page: https://github.com/zhangzimin/whereami
Author: ZhangZimin
Author-email: 641945043@qq.com
License: MIT
Classifier: Programming Language :: Python :: 3
Classifier: License :: OSI Approved :: MIT License
Classifier: Operating System :: OS Independent
Requires-Python: >=3.6
License-File: LICENSE
Requires-Dist: geocoder>=1.38.1
Requires-Dist: rich>=13.7.0
Dynamic: author
Dynamic: author-email
Dynamic: classifier
Dynamic: description
Dynamic: description-content-type
Dynamic: home-page
Dynamic: license
Dynamic: license-file
Dynamic: requires-dist
Dynamic: requires-python
Dynamic: summary
